README
setup.py
venv_easy/__init__.py
venv_easy/install_dependancies.py
venv_easy/venv.py
venv_easy/venvBase.py
venv_easy.egg-info/PKG-INFO
venv_easy.egg-info/SOURCES.txt
venv_easy.egg-info/dependency_links.txt
venv_easy.egg-info/not-zip-safe
venv_easy.egg-info/top_level.txt