Metadata-Version: 1.0
Name: venv-easy
Version: 0.1
Summary: Easily automating virtual environment creation and implementation from within your Python3 Application.
Home-page: https://github.com/AndrewNeudegg/venv_easy
Author: Andrew Neudegg
Author-email: andrew.neudegg@gmail.com
License: MIT
Platform: UNKNOWN
